MANIFEST.in
README.rst
setup.py
dumpey/__init__.py
dumpey/dumpey.py
dumpey.egg-info/PKG-INFO
dumpey.egg-info/SOURCES.txt
dumpey.egg-info/dependency_links.txt
dumpey.egg-info/entry_points.txt
dumpey.egg-info/requires.txt
dumpey.egg-info/top_level.txt
tests/__init__.py
tests/test_dumpey.py