Metadata-Version: 1.1
Name: dumpey
Version: 0.8.3
Summary: Android Debug Bridge utility tool
Home-page: https://github.com/tslamic/Dumpey
Author: Tadej Slamic
Author-email: sljamca@yahoo.com
License: MIT
Keywords: android adb utility dumpey
Platform: UNKNOWN
Classifier: Development Status :: 4 - Beta
Classifier: Environment :: Console
Classifier: Topic :: Utilities
Classifier: License :: OSI Approved :: MIT License
